porder/__init__.py
porder/__main__.py
porder/async_down.py
porder/async_downloader.py
porder/author.py
porder/bundles.json
porder/downloader.py
porder/geojson2id.py
porder/order_now.py
porder/ordstat.py
porder/porder.py
porder/resubmit.py
porder/text_split.py
porder-0.8.7.dist-info/LICENSE
porder-0.8.7.dist-info/METADATA
porder-0.8.7.dist-info/WHEEL
porder-0.8.7.dist-info/entry_points.txt
porder-0.8.7.dist-info/top_level.txt
porder-0.8.7.dist-info/RECORD
