Metadata-Version: 2.1
Name: porder
Version: 0.8.7
Summary: Simple CLI for Planet Orders v2
Home-page: https://github.com/samapriya/porder
Author: Samapriya Roy
Author-email: samapriya.roy@gmail.com
License: Apache 2.0
Platform: UNKNOWN
Classifier: Development Status :: 3 - Alpha
Classifier: Intended Audience :: Developers
Classifier: Intended Audience :: Science/Research
Classifier: Natural Language :: English
Classifier: License :: OSI Approved :: Apache Software License
Classifier: Programming Language :: Python :: 3
Classifier: Programming Language :: Python :: 3.6
Classifier: Programming Language :: Python :: 3.7
Classifier: Programming Language :: Python :: 3.8
Classifier: Operating System :: OS Independent
Classifier: Topic :: Scientific/Engineering :: GIS
Requires-Python: >=3.4
Requires-Dist: requests (>=2.21.1)
Requires-Dist: planet (>=2.0.0b1)
Requires-Dist: retrying (>=1.3.3)
Requires-Dist: progressbar2 (>=3.38.0)
Requires-Dist: visvalingamwyatt (>=0.1.2)
Requires-Dist: DateTimeRange (>=0.6.1)
Requires-Dist: beautifulsoup4
Requires-Dist: logzero
Requires-Dist: PyJWT (==2.6.0)
Requires-Dist: clipboard (>=0.0.4)
Requires-Dist: pyyaml (>=3.12)
Requires-Dist: prettytable (>=0.7.2)
Requires-Dist: pyproj (>=1.9.5.1) ; platform_system != "Windows"
Requires-Dist: shapely (>=1.6.4) ; platform_system != "Windows"
Requires-Dist: fiona (>=1.8.6) ; platform_system != "Windows"
Requires-Dist: geopandas (>=0.5.0) ; platform_system != "Windows"
Requires-Dist: pySmartDL (==1.2.5) ; python_version < "3.4"
Requires-Dist: pySmartDL (>=1.3.1) ; python_version > "3.4"
